LFSR/lfsr.v

module LFSR (clk, rst, seed, out);

parameter WIDTH = 4;

input clk, rst;
input       [WIDTH-1:0] seed;
output reg  [WIDTH-1:0] out;

always @(posedge clk or negedge rst) begin
  if (!rst) out <= seed;
  else out <= {out[WIDTH-2:0], out[WIDTH-1] ^ out[WIDTH-2]};
end

endmodule

util/clock_gen.v
`timescale 1ns/1ps

module clock_gen #(parameter FREQ =1, /*in KHz*/
                             PHASE=0, /*in degrees*/
                             DUTY =50 /*in percentage*/)
                  (enable, clk);
input wire enable;
output reg clk;


real clk_pd     = 1.0/(FREQ * 1e3) * 1e9;   // convert to ns
real clk_on     = DUTY/100.0 * (1.0/(FREQ * 1e3) * 1e9);
real clk_off    = (100.0 - DUTY) / 100.0 * (1.0/(FREQ * 1e3) * 1e9);
real quarter    = (1.0/(FREQ * 1e3) * 1e9) /4;
real start_dly  = ((1.0/(FREQ * 1e3) * 1e9)/4) * PHASE/90;

reg start_clk;


initial begin
  $display("FREQ      = %0d kHz", FREQ);
  $display("PHASE     = %0d deg", PHASE);
  $display("DUTY      = %0d %%", DUTY);

  $display("PERIOD    = %0.3f ns", clk_pd);
  $display("CLK_ON    = %0.3f ns", clk_on);
  $display("CLK_OFF   = %0.3f ns", clk_off);
  $display("QUARTER   = %0.3f ns", quarter);
  $display("START_DLY = %0.3f ns", start_dly);
end

initial begin
  clk <= 0;
  start_clk <= 0;
end

// When clock is enabled, delay driving the clock to one in order
// to acheive the phase effect. start_dely is configured to the
// correct delay for the configured phase. When enable is 0,
// allow engough time to complete the current clock period.
always @(posedge enable or negedge enable) begin
  if (enable) begin
    #(start_dly) start_clk = 1;
  end else begin
    #(start_dly) start_clk = 0;
  end
end

// Achieve duty cycle by a skewed clock on/off time and let this
// run as long as the clocks are turned on.
always @(posedge start_clk) begin
  if (start_clk) begin
    clk = 1;
    while (start_clk) begin
      #(clk_on)   clk = 0;
      #(clk_off)  clk = 1;
    end
    clk = 0;
  end
end
endmodule

building_blocks/LFSR/lfsr_tb.v
`include "../util/clock_gen.v"
`include "lfsr.v"

module lfsr_tb;

// Clock
reg clk_enable;
wire clk;
clock_gen #(.FREQ(200000)) clk_gen(clk_enable, clk);
initial begin
  clk_enable <= 1;
end

// dump waveform
initial begin
  $dumpfile("lfsr_tb.vcd");
  $dumpvars(0, lfsr_tb);
end

// lfsr
reg rst;
reg   [3:0] seed;
wire  [3:0] out;

LFSR #(.WIDTH(4)) uut (.clk(clk), .rst(rst), .seed(seed), .out(out));

initial begin
  seed    <= 4'b1111;
  #5 rst  <= 0;
  #5 rst  <= 1;

  #100 $finish;
end

endmodule

building_blocks/LFSR/lfsr_tb.vcd
$date
	Wed Jul 26 21:49:06 2023
$end
$version
	Icarus Verilog
$end
$timescale
	1ps
$end
$scope module lfsr_tb $end
$var wire 4 ! out [3:0] $end
$var wire 1 " clk $end
$var reg 1 # clk_enable $end
$var reg 1 $ rst $end
$var reg 4 % seed [3:0] $end
$scope module clk_gen $end
$var wire 1 # enable $end
$var reg 1 " clk $end
$var reg 1 & start_clk $end
$var real 1 ' clk_off $end
$var real 1 ( clk_on $end
$var real 1 ) clk_pd $end
$var real 1 * quarter $end
$var real 1 + start_dly $end
$upscope $end
$scope module uut $end
$var wire 1 " clk $end
$var wire 1 $ rst $end
$var wire 4 , seed [3:0] $end
$var reg 4 - out [3:0] $end
$upscope $end
$upscope $end
$enddefinitions $end
#0
$dumpvars
bx -
b1111 ,
r0 +
r1.25 *
r5 )
r2.5 (
r2.5 '
1&
b1111 %
x$
1#
1"
bx !
$end
#2500
0"
#5000
b1111 !
b1111 -
0$
1"
#7500
0"
#10000
1$
1"
#12500
0"
#15000
b1110 !
b1110 -
1"
#17500
0"
#20000
b1100 !
b1100 -
1"
#22500
0"
#25000
b1000 !
b1000 -
1"
#27500
0"
#30000
b1 !
b1 -
1"
#32500
0"
#35000
b10 !
b10 -
1"
#37500
0"
#40000
b100 !
b100 -
1"
#42500
0"
#45000
b1001 !
b1001 -
1"
#47500
0"
#50000
b11 !
b11 -
1"
#52500
0"
#55000
b110 !
b110 -
1"
#57500
0"
#60000
b1101 !
b1101 -
1"
#62500
0"
#65000
b1010 !
b1010 -
1"
#67500
0"
#70000
b101 !
b101 -
1"
#72500
0"
#75000
b1011 !
b1011 -
1"
#77500
0"
#80000
b111 !
b111 -
1"
#82500
0"
#85000
b1111 !
b1111 -
1"
#87500
0"
#90000
b1110 !
b1110 -
1"
#92500
0"
#95000
b1100 !
b1100 -
1"
#97500
0"
#100000
b1000 !
b1000 -
1"
#102500
0"
#105000
b1 !
b1 -
1"
#107500
0"
#110000
b10 !
b10 -
1"
